{
  "solvedByCurrentUser": false,
  "id": 376,
  "elo": 1410.9521283697,
  "problemLevel": 25,
  "rank": {
    "value": 5,
    "unit": "kyu",
    "exact": false,
    "mark": false
  },
  "hasNegativeFlags": false,
  "flagStats": {
    "flags": [],
    "userFlag": null,
    "positiveFlagSum": 0,
    "negativeFlagSum": 0,
    "flagSum": 0
  },
  "isCanon": false,
  "isStandard": false,
  "genre": "endgame",
  "specificGenre": "endgame",
  "description": "",
  "rating": {
    "stars": 3,
    "votes": 10,
    "currentUserVote": null
  },
  "sgf": "(;GM[1]FF[3]\nRU[Japanese]SZ[19]HA[0]KM[5.5]\nPW[White]\nPB[Black]\nGN[White (W) vs. Black (B)]\nDT[1999-07-28]\nSY[Cgoban 1.9.2]TM[30:00(5x1:00)]\nC[best endgame for black on the left side?\n]\nAW[ce][ge][cf][df][ef][ff][gf][bg][cg][hg][ah][gi][bk][dk][gk][cl][bm][dm][em][gm][bn][en][fo][go][cp]\nAB[bc][ad][cd][fd][gd][id][be][de][ee][fe][he][af][bf][ag][bl][cm][cn][bo][do][bp][dp][fp][gp][hp][cq]\n(;B[bh];W[ai]\n(;B[aj];W[bi]\n(;B[bj];W[ci]\n(;B[al]C[RIGHT\nblack catches two stones\n])\n\n(;B[cj];W[al])\n\n(;B[ak];W[al])\n\n(;B[am];W[al])\n\n(;B[an];W[al])\n)\n\n(;B[al];W[ak];B[bj];W[cj])\n\n(;B[ak];W[al])\n\n(;B[ci];W[bj])\n)\n\n(;B[bi];W[aj]\n(;B[bj];W[ak]\n(;B[al];W[am])\n\n(;B[cj];W[al])\n)\n\n(;B[al];W[ak])\n)\n\n(;B[al];W[ak])\n)\n\n(;B[al];W[ak]\n(;B[ai];W[bh])\n\n(;B[bh];W[ai];B[bi];W[aj];B[bj];W[am])\n)\n\n(;B[an];W[al]C[black can do better\n])\n\n(;B[ak];W[al])\n\n(;B[ai];W[bh]\n(;B[al];W[ak])\n\n(;B[an];W[al])\n)\n\n(;B[bi];W[bh]\n(;B[al];W[ak])\n\n(;B[an];W[al])\n)\n\n(;B[cj];W[al])\n\n(;B[dn];W[al])\n\n(;B[am];W[al];B[ao];W[an])\n\n)\n",
  "author": {
    "id": 1,
    "name": "adum",
    "avatar": {
      "current": true,
      "sources": [
        {
          "url": "https://d14j2ume0sa4nc.cloudfront.net/avatars/267_64x64.png",
          "size": 64
        },
        {
          "url": "https://d14j2ume0sa4nc.cloudfront.net/avatars/267_512x512.png",
          "size": 512
        },
        {
          "url": "https://d14j2ume0sa4nc.cloudfront.net/avatars/267_1024x1024.png",
          "size": 1024
        }
      ],
      "id": 267
    },
    "lastOnlineAt": "2026-04-15",
    "rank": {
      "value": 1,
      "unit": "dan",
      "exact": false,
      "mark": false
    },
    "displayRank": {
      "value": 3,
      "unit": "dan",
      "exact": false,
      "mark": false
    },
    "elo": 1545.17
  },
  "avgSolveTimeSeconds": 41,
  "attempts": {
    "solved": 1562,
    "failed": 3924,
    "tries": 5486,
    "speedSolved": 0,
    "speedPlay": 1
  },
  "currentUserAttempts": {
    "solved": 0,
    "failed": 0,
    "tries": 0,
    "speedSolved": 0,
    "speedPlay": 0
  },
  "isFavorited": false,
  "canBeEdited": false,
  "createdAt": "2001-01-31T11:33:02+00:00",
  "source": "game vs len",
  "playerColor": "black",
  "collections": [
    {
      "id": 47,
      "name": "Amateur Game",
      "core": true,
      "privacy": "public"
    }
  ],
  "commentsCount": 7,
  "suggestionsOpenCount": 0,
  "userData": {
    "attempts": {
      "solved": 0,
      "failed": 0,
      "tries": 0,
      "speedSolved": 0,
      "speedPlay": 0
    },
    "isFavorited": false,
    "canBeEdited": false
  },
  "allowSuggestedDifficulty": false,
  "alive": true,
  "sandbox": false,
  "suggestedElo": null
}