{
  "solvedByCurrentUser": false,
  "id": 53993,
  "elo": 1347.9408222836,
  "problemLevel": 23,
  "rank": {
    "value": 5,
    "unit": "kyu",
    "exact": false,
    "mark": true
  },
  "hasNegativeFlags": false,
  "flagStats": {
    "flags": [],
    "userFlag": null,
    "positiveFlagSum": 0,
    "negativeFlagSum": 0,
    "flagSum": 0
  },
  "isCanon": false,
  "isStandard": true,
  "genre": "tesuji",
  "specificGenre": "tesuji",
  "description": "",
  "rating": null,
  "sgf": "(;FF[4]GM[1]CA[UTF-8]AP[goproblems:0.1.0]SZ[13]AB[bd][bc][cc][dc][eb][fb][gc][hc][ed][ce]AW[db][cb][ec][fc][fd][cd][dd][de][be][bf][gb][hb][ib]AN[2](;B[ee];W[df](;B[fe];W[gd](;B[hd];W[ge];B[gf];W[he];B[ie]C[RIGHT])(;B[ge];W[hd]))(;B[ge];W[fa])(;B[gd];W[fe])(;B[ef];W[ge]))(;B[fe];W[ee];B[gd];W[ed])(;B[df];W[ee])(;B[cf];W[ee])(;B[bb];W[fa])(;B[gd];W[fe]))",
  "author": {
    "id": 44133,
    "name": "seeker1987",
    "avatar": {
      "current": true,
      "sources": [
        {
          "url": "https://d14j2ume0sa4nc.cloudfront.net/avatars/1331_64x64.png",
          "size": 64
        },
        {
          "url": "https://d14j2ume0sa4nc.cloudfront.net/avatars/1331_512x512.png",
          "size": 512
        },
        {
          "url": "https://d14j2ume0sa4nc.cloudfront.net/avatars/1331_1024x1024.png",
          "size": 1024
        }
      ],
      "id": 1331
    },
    "lastOnlineAt": "2026-04-16",
    "rank": {
      "value": 7,
      "unit": "dan",
      "exact": false,
      "mark": false
    },
    "displayRank": {
      "value": 7,
      "unit": "dan",
      "exact": false,
      "mark": false
    },
    "elo": 1843.52
  },
  "avgSolveTimeSeconds": 21,
  "attempts": {
    "solved": 3,
    "failed": 2,
    "tries": 5,
    "speedSolved": 0,
    "speedPlay": 1
  },
  "currentUserAttempts": {
    "solved": 0,
    "failed": 0,
    "tries": 0,
    "speedSolved": 0,
    "speedPlay": 0
  },
  "isFavorited": false,
  "canBeEdited": false,
  "createdAt": "2025-12-24T11:30:10+00:00",
  "source": "",
  "playerColor": "black",
  "collections": [
    {
      "id": 53,
      "name": "Ladder",
      "core": true,
      "privacy": "public"
    }
  ],
  "commentsCount": 0,
  "suggestionsOpenCount": 0,
  "userData": {
    "attempts": {
      "solved": 0,
      "failed": 0,
      "tries": 0,
      "speedSolved": 0,
      "speedPlay": 0
    },
    "isFavorited": false,
    "canBeEdited": false
  },
  "allowSuggestedDifficulty": false,
  "alive": true,
  "sandbox": false,
  "suggestedElo": 1400
}