{
  "solvedByCurrentUser": false,
  "id": 9511,
  "elo": 1288.9810140041,
  "problemLevel": 21,
  "rank": {
    "value": 9,
    "unit": "kyu",
    "exact": false,
    "mark": false
  },
  "hasNegativeFlags": false,
  "flagStats": {
    "flags": [],
    "userFlag": null,
    "positiveFlagSum": 5,
    "negativeFlagSum": 0,
    "flagSum": 5
  },
  "isCanon": false,
  "isStandard": false,
  "genre": "tesuji",
  "specificGenre": "tesuji",
  "description": "",
  "rating": {
    "stars": 3.7,
    "votes": 20,
    "currentUserVote": null
  },
  "sgf": "(;AB[dq]AB[eq]AB[cp]AB[jh]AB[jg]LB[do:A]LB[jj:T]AW[dp]AW[dd]AW[qp]AW[np]AW[qd]C[Play A if you think the ladder works or T for tenuki.]AP[goproblems]\r\n(;B[jj]C[Correct, the ladder does not work.RIGHT])\r\n(;B[do];W[ep];B[fp];W[eo]AB[en]AW[fo]AB[go]AW[fn]AB[fm]AW[gn]AB[hn]AW[gm]AB[gl]AW[hm]AB[im]AW[hl]AB[hk]AW[il]AB[jl]AW[ik]AB[ij]AW[jk]AB[kk]AW[jj]\r\n(;B[kj];W[ji]\r\n(;B[ii];W[ki];B[li];W[kh]\r\n(;B[kg];W[lh];B[mh]AW[lg]AB[lf]AW[mg]AB[ng]AW[mf]AB[me]AW[nf]AB[of]AW[ne]AB[nd]AW[oe]AB[pe]AW[od]AB[oc]AW[pd]C[White has escaped.])\r\n(;B[lh];W[kg];B[kf]AW[lg]AB[mg]AW[lf]AB[le]AW[mf]AB[nf]AW[me]AB[md]AW[ne]AB[oe]AW[nd]AB[nc]AW[od]AB[pd]AW[oc]AB[ob]AW[pc]C[White has escaped.]))\r\n(;B[ki];W[ii]C[White has escaped.];B[hi];W[hj];B[ih];W[gk]))\r\n(;B[ji];W[kj];B[lj];W[ki]\r\n(;B[kh];W[li];B[mi]AW[lh]AB[lg]AW[mh]AB[nh]AW[mg]AB[mf]AW[ng]AB[og]AW[nf]AB[ne]AW[of]AB[pf]AW[oe]AB[od]AW[pe]AB[qe]AW[pd]C[White has escaped.])\r\n(;B[li];W[kh]\r\n(;B[kg];W[lh];B[mh];W[lg];B[lf]AW[mg]AB[ng]AW[mf]AB[me]AB[of]AW[nf]AW[ne]AB[nd]AW[oe]AB[pe]AW[od]AB[oc]AW[pd]C[White has escaped.])\r\n(;B[lh];W[kg];B[kf];W[lg];B[mg]AW[lf]AB[le]AB[nf]AW[mf]AW[me]AB[md]AW[ne]AW[nd]AW[od]AB[oe]AB[nc]AB[pd]AW[oc]AB[ob]AW[pc]C[White has escaped.])))))",
  "author": {
    "id": 16859,
    "name": "MatheusB",
    "avatar": {
      "current": true,
      "sources": [
        {
          "url": "https://goproblems.com/build/images/avatar_placeholder64.jpeg",
          "size": 64
        },
        {
          "url": "https://goproblems.com/build/images/avatar_placeholder512.jpeg",
          "size": 512
        },
        {
          "url": "https://goproblems.com/build/images/avatar_placeholder1024.jpeg",
          "size": 1024
        }
      ],
      "id": null
    },
    "lastOnlineAt": "2010-02-23",
    "rank": {
      "value": 29,
      "unit": "kyu",
      "exact": false,
      "mark": false
    },
    "displayRank": {
      "value": 29,
      "unit": "kyu",
      "exact": false,
      "mark": false
    },
    "elo": 700
  },
  "avgSolveTimeSeconds": 46,
  "attempts": {
    "solved": 3583,
    "failed": 4037,
    "tries": 7620,
    "speedSolved": 0,
    "speedPlay": 2
  },
  "currentUserAttempts": {
    "solved": 0,
    "failed": 0,
    "tries": 0,
    "speedSolved": 0,
    "speedPlay": 0
  },
  "isFavorited": false,
  "canBeEdited": false,
  "createdAt": "2006-11-29T02:54:18+00:00",
  "source": "My mind.",
  "playerColor": "black",
  "collections": [
    {
      "id": 53,
      "name": "Ladder",
      "core": true,
      "privacy": "public"
    }
  ],
  "commentsCount": 8,
  "suggestionsOpenCount": 0,
  "userData": {
    "attempts": {
      "solved": 0,
      "failed": 0,
      "tries": 0,
      "speedSolved": 0,
      "speedPlay": 0
    },
    "isFavorited": false,
    "canBeEdited": false
  },
  "allowSuggestedDifficulty": false,
  "alive": true,
  "sandbox": false,
  "suggestedElo": null
}