{
  "solvedByCurrentUser": false,
  "id": 7160,
  "elo": 1122.2803602361,
  "problemLevel": 15,
  "rank": {
    "value": 15,
    "unit": "kyu",
    "exact": false,
    "mark": false
  },
  "hasNegativeFlags": false,
  "flagStats": {
    "flags": [],
    "userFlag": null,
    "positiveFlagSum": 2,
    "negativeFlagSum": 0,
    "flagSum": 2
  },
  "isCanon": true,
  "isStandard": true,
  "genre": "life and death",
  "specificGenre": "life and death",
  "description": "",
  "rating": {
    "stars": 4,
    "votes": 19,
    "currentUserVote": null
  },
  "sgf": "(;AP[goproblems]AB[ap]AB[bp]AB[cp]AB[dq]AB[dr]AB[ds]AW[es]AW[er]AW[eq]AW[ep]AW[dp]AW[do]AW[co]AW[bo]AW[ao]AB[cr]AW[br]C[Black to live. (pssst ... beware of the ko !)](;B[bq];W[as]C[Ko :(])(;B[ar];W[bs](;B[bq]C[Seki :)RIGHT])(;B[aq];W[as]C[dead :(])(;B[as];W[aq]C[???])(;B[cq];W[as](;B[aq]C[dead :(])(;B[bq];W[aq]C[ko :(]))(;B[cs];W[cq]C[???]))(;B[bs];W[aq](;B[cq];W[as]C[Ko :(])(;B[ar];W[as]C[Ko :(]))(;B[aq];W[ar](;B[bs];W[cq])(;B[cq];W[bs]C[dead :(]))(;B[as];W[aq](;B[bs];W[cq])(;B[cq];W[bs]C[dead :(]))(;B[cq];W[bs](;B[ar];W[as](;B[bq];W[aq])(;B[aq]C[argh... suicide]))(;B[aq];W[ar])(;B[bq];W[ar]))(;B[cs];W[bs]))",
  "author": {
    "id": 8645,
    "name": "tom111",
    "avatar": {
      "current": true,
      "sources": [
        {
          "url": "https://goproblems.com/build/images/avatar_placeholder64.jpeg",
          "size": 64
        },
        {
          "url": "https://goproblems.com/build/images/avatar_placeholder512.jpeg",
          "size": 512
        },
        {
          "url": "https://goproblems.com/build/images/avatar_placeholder1024.jpeg",
          "size": 1024
        }
      ],
      "id": null
    },
    "lastOnlineAt": "2025-03-04",
    "rank": {
      "value": 5,
      "unit": "kyu",
      "exact": false,
      "mark": false
    },
    "displayRank": {
      "value": 5,
      "unit": "kyu",
      "exact": false,
      "mark": false
    },
    "elo": 1402.59
  },
  "avgSolveTimeSeconds": 28,
  "attempts": {
    "solved": 5539,
    "failed": 7505,
    "tries": 13044,
    "speedSolved": 9,
    "speedPlay": 22
  },
  "currentUserAttempts": {
    "solved": 0,
    "failed": 0,
    "tries": 0,
    "speedSolved": 0,
    "speedPlay": 0
  },
  "isFavorited": false,
  "canBeEdited": false,
  "createdAt": "2005-08-29T00:26:04+00:00",
  "source": "korean problem acadamy",
  "playerColor": "black",
  "collections": [
    {
      "id": 73,
      "name": "Corner based",
      "core": false,
      "privacy": "public"
    },
    {
      "id": 119,
      "name": "Ko / Ko Threats",
      "core": false,
      "privacy": "public"
    }
  ],
  "commentsCount": 3,
  "suggestionsOpenCount": 0,
  "userData": {
    "attempts": {
      "solved": 0,
      "failed": 0,
      "tries": 0,
      "speedSolved": 0,
      "speedPlay": 0
    },
    "isFavorited": false,
    "canBeEdited": false
  },
  "allowSuggestedDifficulty": false,
  "alive": true,
  "sandbox": false,
  "suggestedElo": null
}