{
  "solvedByCurrentUser": false,
  "id": 10732,
  "elo": 1206.5597661318,
  "problemLevel": 18,
  "rank": {
    "value": 12,
    "unit": "kyu",
    "exact": false,
    "mark": false
  },
  "hasNegativeFlags": false,
  "flagStats": {
    "flags": [],
    "userFlag": null,
    "positiveFlagSum": 3,
    "negativeFlagSum": 0,
    "flagSum": 3
  },
  "isCanon": true,
  "isStandard": true,
  "genre": "life and death",
  "specificGenre": "life and death",
  "description": "",
  "rating": {
    "stars": 3.7,
    "votes": 25,
    "currentUserVote": null
  },
  "sgf": "(;AW[mp]AW[lp]AW[kp]AW[jp]AW[kq]AW[mq]AW[nq]AW[no]AW[oo]AW[nm]AW[ml]AW[ll]AW[lm]AW[km]AW[kn]AW[jo]AW[io]AB[jq]AB[iq]AB[ir]AB[kr]AB[lr]AB[lq]AB[mr]AB[nr]AB[oq]AB[op]AB[np]AB[pp]AB[po]AB[pn]AB[pm]AB[pl]AB[ol]AB[nl]AB[ok]AB[nj]AB[mi]AW[kk]AW[kj]AW[ki]AW[ji]AB[kh]AB[jh]AB[ih]AB[jj]AB[ii]AB[jk]AB[il]AB[jm]AB[jn]AW[jl]AB[in]AB[hn]AB[hm]AB[hk]AB[hj]AB[gp]C[Of course, Black might think she can't miss a chance like this... How do you anwser?]AB[mn]MA[mn]AP[goproblems]\n(;W[mo]C[RIGHT])\n(;W[nn];B[lo]\n(;W[mo];B[ln]C[A seki is indeed life albeit one without any points...RIGHT])\n(;W[ln];B[mo]MA[mm]C[White can be forced to fill N7, leaving a dead shape inside...]))\n(;W[lo];B[nn];W[on];B[mo]C[White is ruined...])\n(;W[on];B[mo]C[White can't prevent both the capture of the 3 stones and the creation of a dead shape inside...]MA[lo]MA[nn])\n(;W[ln];B[nn];W[on];B[mo]C[White is ruined...])\n(;W[om];B[on];W[nn];B[mo];W[mm];B[lo]C[Dead shape inside...]))",
  "author": {
    "id": 4285,
    "name": "santa c",
    "avatar": {
      "current": true,
      "sources": [
        {
          "url": "https://goproblems.com/build/images/avatar_placeholder64.jpeg",
          "size": 64
        },
        {
          "url": "https://goproblems.com/build/images/avatar_placeholder512.jpeg",
          "size": 512
        },
        {
          "url": "https://goproblems.com/build/images/avatar_placeholder1024.jpeg",
          "size": 1024
        }
      ],
      "id": null
    },
    "lastOnlineAt": "2026-04-16",
    "rank": {
      "value": 3,
      "unit": "dan",
      "exact": false,
      "mark": false
    },
    "displayRank": {
      "value": 6,
      "unit": "dan",
      "exact": false,
      "mark": false
    },
    "elo": 1601.61
  },
  "avgSolveTimeSeconds": 64,
  "attempts": {
    "solved": 1677,
    "failed": 2725,
    "tries": 4402,
    "speedSolved": 2,
    "speedPlay": 21
  },
  "currentUserAttempts": {
    "solved": 0,
    "failed": 0,
    "tries": 0,
    "speedSolved": 0,
    "speedPlay": 0
  },
  "isFavorited": false,
  "canBeEdited": false,
  "createdAt": "2007-12-29T04:42:17+00:00",
  "source": "wintogo8d+ vs kokonattsu6d+ (igs)",
  "playerColor": "white",
  "collections": [
    {
      "id": 29,
      "name": "Middle based",
      "core": false,
      "privacy": "public"
    },
    {
      "id": 52,
      "name": "Basic Shape",
      "core": false,
      "privacy": "public"
    }
  ],
  "commentsCount": 6,
  "suggestionsOpenCount": 0,
  "userData": {
    "attempts": {
      "solved": 0,
      "failed": 0,
      "tries": 0,
      "speedSolved": 0,
      "speedPlay": 0
    },
    "isFavorited": false,
    "canBeEdited": false
  },
  "allowSuggestedDifficulty": false,
  "alive": true,
  "sandbox": false,
  "suggestedElo": null
}