{
  "solvedByCurrentUser": false,
  "id": 45864,
  "elo": 1470.7626747987,
  "problemLevel": 27,
  "rank": {
    "value": 3,
    "unit": "kyu",
    "exact": false,
    "mark": true
  },
  "hasNegativeFlags": false,
  "flagStats": {
    "flags": [],
    "userFlag": null,
    "positiveFlagSum": 0,
    "negativeFlagSum": 0,
    "flagSum": 0
  },
  "isCanon": false,
  "isStandard": true,
  "genre": "tesuji",
  "specificGenre": "tesuji",
  "description": "",
  "rating": null,
  "sgf": "(;GM[1]AB[pc][qc][rc][rd][se][rf][od][oe][nf][ng][nh][oh][qh][qg][pe]AW[sd][sc][sb][rb][qb][pb][oc][nb][nd][ne][mf][mg][mh][ni][oi][pi][qi][rh][pd]GN[GZP1](;W[of];B[og](;W[qe]C[RIGHT])(;W[pf];B[qe])(;W[qd];B[qe])(;W[re];B[qe])(;W[ph];B[pf])(;W[pg];B[pf])(;W[qf];B[pf](;W[qe];B[qd])(;W[qd];B[qe])))(;W[ph];B[of](;W[pg];B[pf])(;W[qe];B[qf]))(;W[pg];B[ph](;W[of];B[pf])(;W[qe];B[qd]))(;W[pf];B[of](;W[ph];B[pg])(;W[pg];B[ph]))(;W[qe];B[qf](;W[ph];B[of])(;W[of];B[pf](;W[ph];B[og])(;W[pg];B[ph])(;W[og];B[pg]))(;W[pf];B[of](;W[ph];B[pg])(;W[pg];B[ph]))))",
  "author": {
    "id": 109623,
    "name": "Andjey44",
    "avatar": {
      "current": true,
      "sources": [
        {
          "url": "https://d14j2ume0sa4nc.cloudfront.net/avatars/157_64x64.png",
          "size": 64
        },
        {
          "url": "https://d14j2ume0sa4nc.cloudfront.net/avatars/157_512x512.png",
          "size": 512
        },
        {
          "url": "https://d14j2ume0sa4nc.cloudfront.net/avatars/157_1024x1024.png",
          "size": 1024
        }
      ],
      "id": 157
    },
    "lastOnlineAt": "2026-04-15",
    "rank": {
      "value": 5,
      "unit": "dan",
      "exact": false,
      "mark": false
    },
    "displayRank": {
      "value": 7,
      "unit": "dan",
      "exact": false,
      "mark": false
    },
    "elo": 1726.83
  },
  "avgSolveTimeSeconds": 164,
  "attempts": {
    "solved": 2,
    "failed": 10,
    "tries": 12,
    "speedSolved": 0,
    "speedPlay": 0
  },
  "currentUserAttempts": {
    "solved": 0,
    "failed": 0,
    "tries": 0,
    "speedSolved": 0,
    "speedPlay": 0
  },
  "isFavorited": false,
  "canBeEdited": false,
  "createdAt": "2025-04-23T13:55:08+00:00",
  "source": "",
  "playerColor": "white",
  "collections": [
    {
      "id": 50,
      "name": "GuanZiPu",
      "core": true,
      "privacy": "public"
    }
  ],
  "commentsCount": 1,
  "suggestionsOpenCount": 0,
  "userData": {
    "attempts": {
      "solved": 0,
      "failed": 0,
      "tries": 0,
      "speedSolved": 0,
      "speedPlay": 0
    },
    "isFavorited": false,
    "canBeEdited": false
  },
  "allowSuggestedDifficulty": false,
  "alive": true,
  "sandbox": false,
  "suggestedElo": 1260
}