{
  "solvedByCurrentUser": false,
  "id": 19187,
  "elo": 1156.5993905232,
  "problemLevel": 16,
  "rank": {
    "value": 14,
    "unit": "kyu",
    "exact": false,
    "mark": false
  },
  "hasNegativeFlags": false,
  "flagStats": {
    "flags": [],
    "userFlag": null,
    "positiveFlagSum": 6,
    "negativeFlagSum": 0,
    "flagSum": 6
  },
  "isCanon": true,
  "isStandard": true,
  "genre": "tesuji",
  "specificGenre": "tesuji",
  "description": "",
  "rating": {
    "stars": 4.4,
    "votes": 26,
    "currentUserVote": null
  },
  "sgf": "(;AW[eq]AW[fp]AW[fo]AW[go]AW[hp]AW[ip]AW[jp]AW[jq]AW[jr]AW[hq]AW[hr]AW[lr]AW[lq]AW[lp]AW[lo]AW[ln]AW[kn]AW[in]AW[hm]AW[oq]AB[iq]AB[ir]AB[is]AB[js]AB[hs]AB[kr]AB[kq]AB[kp]AB[ko]AB[jn]AB[km]AB[lm]AB[nm]AB[gp]AB[gq]AB[gr]C[White threatens to cut at two places. How can Black link up to the outside ?]AP[goproblems]\r\n(;B[ho];W[io];B[im]LB[ho:1]LB[io:2]LB[im:3]C[White must play 2, but then the clever move of Black 3 takes advantage of White's shortage of liber­ties to ensure connection. RIGHT])\r\n(;B[jo];W[jm]C[CHOICE])\r\n(;B[ks];W[jo];B[gs];W[fr]C[CHOICE])\r\n(;B[io];W[ho]\r\n(;B[jo];W[jm]C[CHOICE])\r\n(;B[jm];W[jo]C[CHOICE])\r\n(;B[im];W[jo]C[CHOICE]))\r\n(;B[im];W[jo];B[ho];W[jm]C[CHOICE])\r\n(;B[hn];W[jm]\r\n(;B[io];W[jo]C[CHOICE])\r\n(;B[ho];W[jo]C[CHOICE])\r\n(;B[jo];W[io]C[CHOICE]))\r\n(;B[jm];W[jo]C[CHOICE]))",
  "author": {
    "id": 74427,
    "name": "vougalar",
    "avatar": {
      "current": true,
      "sources": [
        {
          "url": "https://goproblems.com/build/images/avatar_placeholder64.jpeg",
          "size": 64
        },
        {
          "url": "https://goproblems.com/build/images/avatar_placeholder512.jpeg",
          "size": 512
        },
        {
          "url": "https://goproblems.com/build/images/avatar_placeholder1024.jpeg",
          "size": 1024
        }
      ],
      "id": null
    },
    "lastOnlineAt": "2024-11-13",
    "rank": {
      "value": 21,
      "unit": "kyu",
      "exact": false,
      "mark": false
    },
    "displayRank": {
      "value": 19,
      "unit": "kyu",
      "exact": false,
      "mark": false
    },
    "elo": 971.933
  },
  "avgSolveTimeSeconds": 109,
  "attempts": {
    "solved": 868,
    "failed": 1478,
    "tries": 2346,
    "speedSolved": 4,
    "speedPlay": 18
  },
  "currentUserAttempts": {
    "solved": 0,
    "failed": 0,
    "tries": 0,
    "speedSolved": 0,
    "speedPlay": 0
  },
  "isFavorited": false,
  "canBeEdited": false,
  "createdAt": "2015-03-13T16:00:00+00:00",
  "source": "varius",
  "playerColor": "black",
  "collections": [
    {
      "id": 177,
      "name": "Tesuji",
      "core": false,
      "privacy": "public"
    }
  ],
  "commentsCount": 4,
  "suggestionsOpenCount": 0,
  "userData": {
    "attempts": {
      "solved": 0,
      "failed": 0,
      "tries": 0,
      "speedSolved": 0,
      "speedPlay": 0
    },
    "isFavorited": false,
    "canBeEdited": false
  },
  "allowSuggestedDifficulty": false,
  "alive": true,
  "sandbox": false,
  "suggestedElo": null
}