{
  "solvedByCurrentUser": false,
  "id": 16010,
  "elo": 943.37385765683,
  "problemLevel": 8,
  "rank": {
    "value": 22,
    "unit": "kyu",
    "exact": false,
    "mark": false
  },
  "hasNegativeFlags": false,
  "flagStats": {
    "flags": [],
    "userFlag": null,
    "positiveFlagSum": 9,
    "negativeFlagSum": 0,
    "flagSum": 9
  },
  "isCanon": true,
  "isStandard": true,
  "genre": "life and death",
  "specificGenre": "life and death",
  "description": "",
  "rating": {
    "stars": 4.2,
    "votes": 25,
    "currentUserVote": null
  },
  "sgf": "(;AP[goproblems]AB[ra]AB[sd]AB[rd]AB[qd]AW[pb]AW[pc]AW[pd]AW[qe]AW[re]AW[rg]C[Black to live](;B[sb];W[qb](;B[rb];W[rc](;B[qc]C[RIGHT])(;B[sc];W[qc]))(;B[rc];W[rb])(;B[qa];W[rb];B[pa];W[oa])(;B[qc];W[rb];B[rc];W[se]))(;B[qc];W[sb](;B[rb];W[sc])(;B[sc];W[rb]))(;B[qb];W[qc](;B[rc];W[sb])(;B[sb];W[rc]))(;B[rb];W[qc](;B[rc];W[sb])(;B[sb];W[rc]))(;B[rc];W[sb])(;B[qa];W[qb](;B[rb];W[qc](;B[sb];W[rc])(;B[rc];W[sb]))(;B[qc];W[rb]))(;B[sc];W[qb](;B[qc];W[rb])(;B[rb];W[qc]))(;B[se];W[qc](;B[rc];W[sb])(;B[sb];W[rc])))",
  "author": {
    "id": 52647,
    "name": "passero",
    "avatar": {
      "current": true,
      "sources": [
        {
          "url": "https://goproblems.com/build/images/avatar_placeholder64.jpeg",
          "size": 64
        },
        {
          "url": "https://goproblems.com/build/images/avatar_placeholder512.jpeg",
          "size": 512
        },
        {
          "url": "https://goproblems.com/build/images/avatar_placeholder1024.jpeg",
          "size": 1024
        }
      ],
      "id": null
    },
    "lastOnlineAt": "2012-08-25",
    "rank": {
      "value": 5,
      "unit": "dan",
      "exact": false,
      "mark": false
    },
    "displayRank": {
      "value": 5,
      "unit": "dan",
      "exact": false,
      "mark": false
    },
    "elo": 1661.55
  },
  "avgSolveTimeSeconds": 31,
  "attempts": {
    "solved": 4371,
    "failed": 4988,
    "tries": 9359,
    "speedSolved": 27,
    "speedPlay": 30
  },
  "currentUserAttempts": {
    "solved": 0,
    "failed": 0,
    "tries": 0,
    "speedSolved": 0,
    "speedPlay": 0
  },
  "isFavorited": false,
  "canBeEdited": false,
  "createdAt": "2012-04-30T01:02:18+00:00",
  "source": "Maeda Elementary Tsumego 14",
  "playerColor": "black",
  "collections": [
    {
      "id": 49,
      "name": "Maeda",
      "core": false,
      "privacy": "public"
    },
    {
      "id": 73,
      "name": "Corner based",
      "core": false,
      "privacy": "public"
    },
    {
      "id": 281,
      "name": "9x9 corner fights",
      "core": false,
      "privacy": "public"
    }
  ],
  "commentsCount": 1,
  "suggestionsOpenCount": 0,
  "userData": {
    "attempts": {
      "solved": 0,
      "failed": 0,
      "tries": 0,
      "speedSolved": 0,
      "speedPlay": 0
    },
    "isFavorited": false,
    "canBeEdited": false
  },
  "allowSuggestedDifficulty": false,
  "alive": true,
  "sandbox": false,
  "suggestedElo": null
}