{
  "solvedByCurrentUser": false,
  "id": 22243,
  "elo": 749.55308312833,
  "problemLevel": 2,
  "rank": {
    "value": 28,
    "unit": "kyu",
    "exact": false,
    "mark": false
  },
  "hasNegativeFlags": false,
  "flagStats": {
    "flags": [],
    "userFlag": null,
    "positiveFlagSum": 0,
    "negativeFlagSum": 0,
    "flagSum": 0
  },
  "isCanon": false,
  "isStandard": false,
  "genre": "tesuji",
  "specificGenre": "tesuji",
  "description": "",
  "rating": {
    "stars": 1.2,
    "votes": 8,
    "currentUserVote": null
  },
  "sgf": "(;SZ[16]AB[ap]AB[bp]AB[cp]AB[dp]AB[ep]AB[fp]AB[gp]AB[hp]AW[ip]AW[jp]AW[kp]AW[lp]AW[mp]AW[np]AW[op]AW[pp]AW[ho]AW[hn]AW[hm]AW[hl]AW[hk]AW[hj]AW[hi]AW[hh]AW[hg]AW[hf]AW[he]AW[hd]AW[hc]AW[hb]AW[ha]AB[io]AB[in]AB[im]AB[ik]AB[il]AB[ii]AB[ij]AB[ih]AB[ig]AB[if]AB[ie]AB[id]AB[ic]AB[ib]AB[ia]AW[ga]AW[fa]AW[ea]AW[da]AW[ca]AW[ba]AW[aa]AW[ab]AB[ja]AB[ka]AB[la]AB[ma]AB[na]AB[oa]AB[pa]AB[pb]AB[go]AB[gn]AB[fn]AB[en]AB[dn]AB[cn]AB[bn]AB[an]AW[jo]AW[jn]AW[kn]AW[ln]AW[mn]AW[nn]AW[pn]AW[on]AW[ac]AW[ad]AW[ae]AW[af]AW[ag]AW[ah]AW[ai]AW[aj]AW[ak]AW[al]AW[am]AB[pc]AB[pe]AB[pd]AB[pg]AB[pf]AB[ph]AB[pi]AB[pj]AB[pl]AB[pk]AB[pm]AB[cm]AB[cl]AB[ck]AB[cj]AB[ci]AB[ch]AB[cg]AB[cf]AB[ce]AB[cd]AB[cc]AB[dc]AB[ec]AB[fc]AB[fd]AB[fe]AB[fg]AB[ff]AB[fh]AB[fi]AB[fj]AB[fl]AB[fk]AB[fm]AW[km]AW[kl]AW[kk]AW[kj]AW[ki]AW[kh]AW[kg]AW[kf]AW[ke]AW[kd]AW[kc]AW[mc]AW[lc]AW[nc]AW[nd]AW[ne]AW[nf]AW[ng]AW[nj]AW[nh]AW[ni]AW[nk]AW[nl]AW[nm]AB[gc]AB[gb]AW[jc]AW[jb]C[Black to play.]AP[goproblems]\n(;B[bm]C[RIGHT])\n(;B[bl]C[RIGHT])\n(;B[bk]C[RIGHT])\n(;B[bj]C[RIGHT])\n(;B[bi]C[RIGHT])\n(;B[bh]C[RIGHT])\n(;B[bg]C[RIGHT])\n(;B[bf]C[RIGHT])\n(;B[be]C[RIGHT])\n(;B[bd]C[RIGHT])\n(;B[bc]C[RIGHT])\n(;B[bb]C[RIGHT])\n(;B[cb]C[RIGHT])\n(;B[db]C[RIGHT])\n(;B[eb]C[RIGHT])\n(;B[fb]C[RIGHT])\n(;B[gd]C[RIGHT])\n(;B[ge]C[RIGHT])\n(;B[gf]C[RIGHT])\n(;B[gg]C[RIGHT])\n(;B[gh]C[RIGHT])\n(;B[gi]C[RIGHT])\n(;B[gj]C[RIGHT])\n(;B[gk]C[RIGHT])\n(;B[gl]C[RIGHT])\n(;B[gm]C[RIGHT])\n(;B[om])\n(;B[ol])\n(;B[ok])\n(;B[oj])\n(;B[oi])\n(;B[oh])\n(;B[og])\n(;B[of])\n(;B[oe])\n(;B[od])\n(;B[oc])\n(;B[ob])\n(;B[nb])\n(;B[mb])\n(;B[lb])\n(;B[kb])\n(;B[jd])\n(;B[je])\n(;B[jf])\n(;B[jg])\n(;B[jh])\n(;B[ji])\n(;B[jj])\n(;B[jk])\n(;B[jl])\n(;B[jm]))",
  "author": {
    "id": 97489,
    "name": "Irregular go",
    "avatar": {
      "current": true,
      "sources": [
        {
          "url": "https://goproblems.com/build/images/avatar_placeholder64.jpeg",
          "size": 64
        },
        {
          "url": "https://goproblems.com/build/images/avatar_placeholder512.jpeg",
          "size": 512
        },
        {
          "url": "https://goproblems.com/build/images/avatar_placeholder1024.jpeg",
          "size": 1024
        }
      ],
      "id": null
    },
    "lastOnlineAt": "2024-09-16",
    "rank": {
      "value": 24,
      "unit": "kyu",
      "exact": false,
      "mark": false
    },
    "displayRank": {
      "value": 24,
      "unit": "kyu",
      "exact": false,
      "mark": false
    },
    "elo": 878.05
  },
  "avgSolveTimeSeconds": 47,
  "attempts": {
    "solved": 418,
    "failed": 121,
    "tries": 539,
    "speedSolved": 0,
    "speedPlay": 12
  },
  "currentUserAttempts": {
    "solved": 0,
    "failed": 0,
    "tries": 0,
    "speedSolved": 0,
    "speedPlay": 0
  },
  "isFavorited": false,
  "canBeEdited": false,
  "createdAt": "2020-01-12T02:25:47+00:00",
  "source": "",
  "playerColor": "black",
  "collections": [
    {
      "id": 18,
      "name": "Semeai / Capturing Race",
      "core": true,
      "privacy": "public"
    }
  ],
  "commentsCount": 0,
  "suggestionsOpenCount": 0,
  "userData": {
    "attempts": {
      "solved": 0,
      "failed": 0,
      "tries": 0,
      "speedSolved": 0,
      "speedPlay": 0
    },
    "isFavorited": false,
    "canBeEdited": false
  },
  "allowSuggestedDifficulty": false,
  "alive": true,
  "sandbox": false,
  "suggestedElo": null
}