{
  "solvedByCurrentUser": false,
  "id": 9753,
  "elo": 1541.2092117957,
  "problemLevel": 30,
  "rank": {
    "value": 1,
    "unit": "dan",
    "exact": false,
    "mark": false
  },
  "hasNegativeFlags": false,
  "flagStats": {
    "flags": [],
    "userFlag": null,
    "positiveFlagSum": 2,
    "negativeFlagSum": 0,
    "flagSum": 2
  },
  "isCanon": false,
  "isStandard": false,
  "genre": "tesuji",
  "specificGenre": "tesuji",
  "description": "",
  "rating": {
    "stars": 4.5,
    "votes": 4,
    "currentUserVote": null
  },
  "sgf": "(;AB[pd]AB[nd]AB[ne]AB[ng]AB[nf]AB[oh]AB[pi]AB[qi]AB[qj]AB[pk]AB[pl]AW[qk]AW[rk]AW[oi]AW[oj]AW[pj]AW[pg]AW[ph]AW[oc]AW[nc]AW[md]AW[me]AW[mf]AB[pc]AB[qe]AB[oq]AB[qp]C[Black to get the best out of his situation]AP[goproblems]\n(;B[qh];W[qg];B[rg];W[rh];B[ri];W[rf];B[sh];W[sf]\n(;B[qf];W[sg]C[Ko])\n(;B[sg];W[sj]\n(;B[qf];W[si])\n(;B[rj];W[sk])))\n(;B[rg];W[qh]\n(;B[rh];W[ri])\n(;B[ri];W[rh]C[This is what I tried in the game. Go on to see if it works...];B[sh];W[rf];B[qf];W[qg]\n(;B[sg];W[sf]\n(;B[si];W[sj])\n(;B[re];W[si])\n(;B[og];W[si]))\n(;B[pf];W[sg];B[si];W[sj])\n(;B[sf];W[rj];B[si];W[sj]C[Black is not happy.])))\n(;B[rm];W[qh]C[White is very glad that you let him connect all his weak stones.])\n(;B[ql];W[rj]C[White is very glad that you let him connect all his weak stones.])\n(;B[ni]C[NOTTHIS])\n(;B[nj]C[NOTTHIS])\n(;B[ok]C[NOTTHIS])\n(;B[rh];W[qh]\n(;B[rg];W[ri])\n(;B[ri];W[rg]\n(;B[og];W[qg];B[sg];W[rj]\n(;B[rf];W[si])\n(;B[sh];W[sf]))\n(;B[pf];W[qg];B[sg];W[rj]\n(;B[rf];W[si])\n(;B[sh];W[sf]))\n(;B[qg];W[qf]\n(;B[pf]\n(;W[re];B[og];W[qg]\n(;B[rd];W[sf];B[se];W[sd];B[sc];W[se];B[sh];W[rj])\n(;B[sg];W[rf];B[rd]C[Yupa!RIGHT])\n(;B[sf];W[rd]\n(;B[rf]C[Right!RIGHT])\n(;B[sg];W[rf])))\n(;W[sg];B[og];W[qg]\n(;B[sf]C[RIGHT])\n(;B[rf];W[re];B[rd];W[sf];B[sd];W[rj])))\n(;B[og];W[pf]\n(;B[rf];W[re])\n(;B[pe];W[re])))\n(;B[rf];W[sg];B[qg];W[qf];B[pf];W[re]C[Ko. You can do better than this.])))\n(;B[ri];W[rh];B[qh];W[qg];B[rg];W[rf];B[sh];W[sf]\n(;B[qf];W[sg]C[Ko])\n(;B[sg];W[sj]\n(;B[qf];W[si])\n(;B[rj];W[sk])))\n(;B[rj];W[qh]\n(;B[rl];W[ri])\n(;B[rh];W[sj])\n(;B[ql];W[ri])\n(;B[sk];W[ri])\n(;B[sj];W[sk];B[rh];W[si])))",
  "author": {
    "id": 11820,
    "name": "om3",
    "avatar": {
      "current": true,
      "sources": [
        {
          "url": "https://goproblems.com/build/images/avatar_placeholder64.jpeg",
          "size": 64
        },
        {
          "url": "https://goproblems.com/build/images/avatar_placeholder512.jpeg",
          "size": 512
        },
        {
          "url": "https://goproblems.com/build/images/avatar_placeholder1024.jpeg",
          "size": 1024
        }
      ],
      "id": null
    },
    "lastOnlineAt": "2009-06-25",
    "rank": {
      "value": 29,
      "unit": "kyu",
      "exact": false,
      "mark": false
    },
    "displayRank": {
      "value": 29,
      "unit": "kyu",
      "exact": false,
      "mark": false
    },
    "elo": 700
  },
  "avgSolveTimeSeconds": 74,
  "attempts": {
    "solved": 760,
    "failed": 1631,
    "tries": 2391,
    "speedSolved": 0,
    "speedPlay": 0
  },
  "currentUserAttempts": {
    "solved": 0,
    "failed": 0,
    "tries": 0,
    "speedSolved": 0,
    "speedPlay": 0
  },
  "isFavorited": false,
  "canBeEdited": false,
  "createdAt": "2007-02-16T16:09:41+00:00",
  "source": "own game",
  "playerColor": "black",
  "collections": [
    {
      "id": 18,
      "name": "Semeai / Capturing Race",
      "core": true,
      "privacy": "public"
    },
    {
      "id": 27,
      "name": "Connect",
      "core": true,
      "privacy": "public"
    },
    {
      "id": 74,
      "name": "Side based",
      "core": false,
      "privacy": "public"
    }
  ],
  "commentsCount": 17,
  "suggestionsOpenCount": 0,
  "userData": {
    "attempts": {
      "solved": 0,
      "failed": 0,
      "tries": 0,
      "speedSolved": 0,
      "speedPlay": 0
    },
    "isFavorited": false,
    "canBeEdited": false
  },
  "allowSuggestedDifficulty": false,
  "alive": true,
  "sandbox": false,
  "suggestedElo": null
}